<annotation>
	<folder>my-project-name</folder>
	<filename>summary_sample.jpg</filename>
	<path>/my-project-name/summary_sample.jpg</path>
	<source>
		<database>Unspecified</database>
	</source>
	<size>
		<width>3840</width>
		<height>2160</height>
		<depth>3</depth>
	</size>
	<object>
		<name>DRIBBLE_SUCCESS_RATE_HOME</name>
		<pose>Unspecified</pose>
		<truncated>0</truncated>
		<difficult>0</difficult>
		<bndbox>
			<xmin>576</xmin>
			<ymin>588</ymin>
			<xmax>820</xmax>
			<ymax>714</ymax>
		</bndbox>
	</object>
	<object>
		<name>SHOT_ACCURACY_HOME</name>
		<pose>Unspecified</pose>
		<truncated>0</truncated>
		<difficult>0</difficult>
		<bndbox>
			<xmin>570</xmin>
			<ymin>1123</ymin>
			<xmax>827</xmax>
			<ymax>1233</ymax>
		</bndbox>
	</object>
	<object>
		<name>PASS_ACCURACY_HOME</name>
		<pose>Unspecified</pose>
		<truncated>0</truncated>
		<difficult>0</difficult>
		<bndbox>
			<xmin>567</xmin>
			<ymin>1651</ymin>
			<xmax>825</xmax>
			<ymax>1746</ymax>
		</bndbox>
	</object>
	<object>
		<name>DRIBBLE_SUCCESS_RATE_AWAY</name>
		<pose>Unspecified</pose>
		<truncated>0</truncated>
		<difficult>0</difficult>
		<bndbox>
			<xmin>3015</xmin>
			<ymin>604</ymin>
			<xmax>3265</xmax>
			<ymax>712</ymax>
		</bndbox>
	</object>
	<object>
		<name>SHOT_ACCURACY_AWAY</name>
		<pose>Unspecified</pose>
		<truncated>0</truncated>
		<difficult>0</difficult>
		<bndbox>
			<xmin>3017</xmin>
			<ymin>1132</ymin>
			<xmax>3267</xmax>
			<ymax>1233</ymax>
		</bndbox>
	</object>
	<object>
		<name>PASS_ACCURACY_AWAY</name>
		<pose>Unspecified</pose>
		<truncated>0</truncated>
		<difficult>0</difficult>
		<bndbox>
			<xmin>3011</xmin>
			<ymin>1649</ymin>
			<xmax>3264</xmax>
			<ymax>1755</ymax>
		</bndbox>
	</object>
	<object>
		<name>POSSESSION_HOME</name>
		<pose>Unspecified</pose>
		<truncated>0</truncated>
		<difficult>0</difficult>
		<bndbox>
			<xmin>1324</xmin>
			<ymin>507</ymin>
			<xmax>1407</xmax>
			<ymax>573</ymax>
		</bndbox>
	</object>
	<object>
		<name>BALL_RECOVERY_TIME_HOME</name>
		<pose>Unspecified</pose>
		<truncated>0</truncated>
		<difficult>0</difficult>
		<bndbox>
			<xmin>1323</xmin>
			<ymin>606</ymin>
			<xmax>1382</xmax>
			<ymax>666</ymax>
		</bndbox>
	</object>
	<object>
		<name>SHOTS_HOME</name>
		<pose>Unspecified</pose>
		<truncated>0</truncated>
		<difficult>0</difficult>
		<bndbox>
			<xmin>1322</xmin>
			<ymin>706</ymin>
			<xmax>1386</xmax>
			<ymax>770</ymax>
		</bndbox>
	</object>
	<object>
		<name>EXPECTED_GOALS_HOME</name>
		<pose>Unspecified</pose>
		<truncated>0</truncated>
		<difficult>0</difficult>
		<bndbox>
			<xmin>1324</xmin>
			<ymin>788</ymin>
			<xmax>1421</xmax>
			<ymax>869</ymax>
		</bndbox>
	</object>
	<object>
		<name>PASSES_HOME</name>
		<pose>Unspecified</pose>
		<truncated>0</truncated>
		<difficult>0</difficult>
		<bndbox>
			<xmin>1327</xmin>
			<ymin>900</ymin>
			<xmax>1419</xmax>
			<ymax>968</ymax>
		</bndbox>
	</object>
	<object>
		<name>TACKLES_HOME</name>
		<pose>Unspecified</pose>
		<truncated>0</truncated>
		<difficult>0</difficult>
		<bndbox>
			<xmin>1324</xmin>
			<ymin>999</ymin>
			<xmax>1413</xmax>
			<ymax>1066</ymax>
		</bndbox>
	</object>
	<object>
		<name>TACKLES_WON_HOME</name>
		<pose>Unspecified</pose>
		<truncated>0</truncated>
		<difficult>0</difficult>
		<bndbox>
			<xmin>1324</xmin>
			<ymin>1092</ymin>
			<xmax>1401</xmax>
			<ymax>1165</ymax>
		</bndbox>
	</object>
	<object>
		<name>INTERCEPTIONS_HOME</name>
		<pose>Unspecified</pose>
		<truncated>0</truncated>
		<difficult>0</difficult>
		<bndbox>
			<xmin>1327</xmin>
			<ymin>1196</ymin>
			<xmax>1411</xmax>
			<ymax>1266</ymax>
		</bndbox>
	</object>
	<object>
		<name>SAVES_HOME</name>
		<pose>Unspecified</pose>
		<truncated>0</truncated>
		<difficult>0</difficult>
		<bndbox>
			<xmin>1328</xmin>
			<ymin>1291</ymin>
			<xmax>1409</xmax>
			<ymax>1355</ymax>
		</bndbox>
	</object>
	<object>
		<name>FOULS_COMMITTED_HOME</name>
		<pose>Unspecified</pose>
		<truncated>0</truncated>
		<difficult>0</difficult>
		<bndbox>
			<xmin>1330</xmin>
			<ymin>1388</ymin>
			<xmax>1415</xmax>
			<ymax>1459</ymax>
		</bndbox>
	</object>
	<object>
		<name>OFFSIDES_HOME</name>
		<pose>Unspecified</pose>
		<truncated>0</truncated>
		<difficult>0</difficult>
		<bndbox>
			<xmin>1330</xmin>
			<ymin>1483</ymin>
			<xmax>1413</xmax>
			<ymax>1562</ymax>
		</bndbox>
	</object>
	<object>
		<name>CORNERS_HOME</name>
		<pose>Unspecified</pose>
		<truncated>0</truncated>
		<difficult>0</difficult>
		<bndbox>
			<xmin>1326</xmin>
			<ymin>1585</ymin>
			<xmax>1415</xmax>
			<ymax>1661</ymax>
		</bndbox>
	</object>
	<object>
		<name>FREE_KICKS_HOME</name>
		<pose>Unspecified</pose>
		<truncated>0</truncated>
		<difficult>0</difficult>
		<bndbox>
			<xmin>1324</xmin>
			<ymin>1680</ymin>
			<xmax>1411</xmax>
			<ymax>1757</ymax>
		</bndbox>
	</object>
	<object>
		<name>PENALTY_KICKS_HOME</name>
		<pose>Unspecified</pose>
		<truncated>0</truncated>
		<difficult>0</difficult>
		<bndbox>
			<xmin>1324</xmin>
			<ymin>1781</ymin>
			<xmax>1421</xmax>
			<ymax>1852</ymax>
		</bndbox>
	</object>
	<object>
		<name>YELLOW_CARDS_HOME</name>
		<pose>Unspecified</pose>
		<truncated>0</truncated>
		<difficult>0</difficult>
		<bndbox>
			<xmin>1323</xmin>
			<ymin>1875</ymin>
			<xmax>1423</xmax>
			<ymax>1953</ymax>
		</bndbox>
	</object>
	<object>
		<name>POSSESSION_AWAY</name>
		<pose>Unspecified</pose>
		<truncated>0</truncated>
		<difficult>0</difficult>
		<bndbox>
			<xmin>2429</xmin>
			<ymin>495</ymin>
			<xmax>2518</xmax>
			<ymax>581</ymax>
		</bndbox>
	</object>
	<object>
		<name>BALL_RECOVERY_TIME_AWAY</name>
		<pose>Unspecified</pose>
		<truncated>0</truncated>
		<difficult>0</difficult>
		<bndbox>
			<xmin>2427</xmin>
			<ymin>598</ymin>
			<xmax>2516</xmax>
			<ymax>687</ymax>
		</bndbox>
	</object>
	<object>
		<name>SHOTS_AWAY</name>
		<pose>Unspecified</pose>
		<truncated>0</truncated>
		<difficult>0</difficult>
		<bndbox>
			<xmin>2435</xmin>
			<ymin>703</ymin>
			<xmax>2513</xmax>
			<ymax>766</ymax>
		</bndbox>
	</object>
	<object>
		<name>EXPECTED_GOALS_AWAY</name>
		<pose>Unspecified</pose>
		<truncated>0</truncated>
		<difficult>0</difficult>
		<bndbox>
			<xmin>2419</xmin>
			<ymin>786</ymin>
			<xmax>2516</xmax>
			<ymax>881</ymax>
		</bndbox>
	</object>
	<object>
		<name>PASSES_AWAY</name>
		<pose>Unspecified</pose>
		<truncated>0</truncated>
		<difficult>0</difficult>
		<bndbox>
			<xmin>2419</xmin>
			<ymin>886</ymin>
			<xmax>2515</xmax>
			<ymax>979</ymax>
		</bndbox>
	</object>
	<object>
		<name>TACKLES_AWAY</name>
		<pose>Unspecified</pose>
		<truncated>0</truncated>
		<difficult>0</difficult>
		<bndbox>
			<xmin>2431</xmin>
			<ymin>981</ymin>
			<xmax>2516</xmax>
			<ymax>1074</ymax>
		</bndbox>
	</object>
	<object>
		<name>TACKLES_WON_AWAY</name>
		<pose>Unspecified</pose>
		<truncated>0</truncated>
		<difficult>0</difficult>
		<bndbox>
			<xmin>2429</xmin>
			<ymin>1078</ymin>
			<xmax>2512</xmax>
			<ymax>1173</ymax>
		</bndbox>
	</object>
	<object>
		<name>INTERCEPTIONS_AWAY</name>
		<pose>Unspecified</pose>
		<truncated>0</truncated>
		<difficult>0</difficult>
		<bndbox>
			<xmin>2425</xmin>
			<ymin>1177</ymin>
			<xmax>2516</xmax>
			<ymax>1268</ymax>
		</bndbox>
	</object>
	<object>
		<name>SAVES_AWAY</name>
		<pose>Unspecified</pose>
		<truncated>0</truncated>
		<difficult>0</difficult>
		<bndbox>
			<xmin>2429</xmin>
			<ymin>1277</ymin>
			<xmax>2515</xmax>
			<ymax>1361</ymax>
		</bndbox>
	</object>
	<object>
		<name>FOULS_COMMITTED_AWAY</name>
		<pose>Unspecified</pose>
		<truncated>0</truncated>
		<difficult>0</difficult>
		<bndbox>
			<xmin>2445</xmin>
			<ymin>1374</ymin>
			<xmax>2518</xmax>
			<ymax>1457</ymax>
		</bndbox>
	</object>
	<object>
		<name>OFFSIDES_AWAY</name>
		<pose>Unspecified</pose>
		<truncated>0</truncated>
		<difficult>0</difficult>
		<bndbox>
			<xmin>2441</xmin>
			<ymin>1471</ymin>
			<xmax>2518</xmax>
			<ymax>1566</ymax>
		</bndbox>
	</object>
	<object>
		<name>CORNERS_AWAY</name>
		<pose>Unspecified</pose>
		<truncated>0</truncated>
		<difficult>0</difficult>
		<bndbox>
			<xmin>2431</xmin>
			<ymin>1568</ymin>
			<xmax>2512</xmax>
			<ymax>1663</ymax>
		</bndbox>
	</object>
	<object>
		<name>FREE_KICKS_AWAY</name>
		<pose>Unspecified</pose>
		<truncated>0</truncated>
		<difficult>0</difficult>
		<bndbox>
			<xmin>2441</xmin>
			<ymin>1665</ymin>
			<xmax>2514</xmax>
			<ymax>1759</ymax>
		</bndbox>
	</object>
	<object>
		<name>PENALTY_KICKS_AWAY</name>
		<pose>Unspecified</pose>
		<truncated>0</truncated>
		<difficult>0</difficult>
		<bndbox>
			<xmin>2431</xmin>
			<ymin>1767</ymin>
			<xmax>2515</xmax>
			<ymax>1864</ymax>
		</bndbox>
	</object>
	<object>
		<name>YELLOW_CARDS_AWAY</name>
		<pose>Unspecified</pose>
		<truncated>0</truncated>
		<difficult>0</difficult>
		<bndbox>
			<xmin>2435</xmin>
			<ymin>1872</ymin>
			<xmax>2516</xmax>
			<ymax>1974</ymax>
		</bndbox>
	</object>
	<object>
		<name>TOTAL_MATCH_TIME</name>
		<pose>Unspecified</pose>
		<truncated>0</truncated>
		<difficult>0</difficult>
		<bndbox>
			<xmin>1790</xmin>
			<ymin>209</ymin>
			<xmax>2032</xmax>
			<ymax>306</ymax>
		</bndbox>
	</object>
	<object>
		<name>SCORE_HOME</name>
		<pose>Unspecified</pose>
		<truncated>0</truncated>
		<difficult>0</difficult>
		<bndbox>
			<xmin>1705</xmin>
			<ymin>60</ymin>
			<xmax>1870</xmax>
			<ymax>234</ymax>
		</bndbox>
	</object>
	<object>
		<name>SCORE_AWAY</name>
		<pose>Unspecified</pose>
		<truncated>0</truncated>
		<difficult>0</difficult>
		<bndbox>
			<xmin>1943</xmin>
			<ymin>62</ymin>
			<xmax>2115</xmax>
			<ymax>232</ymax>
		</bndbox>
	</object>
	<object>
		<name>TEAM_HOME</name>
		<pose>Unspecified</pose>
		<truncated>0</truncated>
		<difficult>0</difficult>
		<bndbox>
			<xmin>979</xmin>
			<ymin>77</ymin>
			<xmax>1595</xmax>
			<ymax>246</ymax>
		</bndbox>
	</object>
	<object>
		<name>TEAM_AWAY</name>
		<pose>Unspecified</pose>
		<truncated>0</truncated>
		<difficult>0</difficult>
		<bndbox>
			<xmin>2276</xmin>
			<ymin>74</ymin>
			<xmax>2810</xmax>
			<ymax>234</ymax>
		</bndbox>
	</object>
	<object>
		<name>PAGE_ID</name>
		<pose>Unspecified</pose>
		<truncated>0</truncated>
		<difficult>0</difficult>
		<bndbox>
			<xmin>401</xmin>
			<ymin>821</ymin>
			<xmax>1012</xmax>
			<ymax>898</ymax>
		</bndbox>
	</object>
</annotation>